uvicore/__init__.py
uvicore/auth/__init__.py
uvicore/auth/auth.py
uvicore/auth/authenticators/__init__.py
uvicore/auth/authenticators/base.py
uvicore/auth/authenticators/basic.py
uvicore/auth/authenticators/jwt.py
uvicore/auth/commands/db.py
uvicore/auth/config/package.py
uvicore/auth/contractsOLD/__init__.py
uvicore/auth/contractsOLD/group.py
uvicore/auth/contractsOLD/user.py
uvicore/auth/contractsOLD/user_info.py
uvicore/auth/database/seeders/__init__.py
uvicore/auth/database/seeders/groups.py
uvicore/auth/database/seeders/permissions.py
uvicore/auth/database/seeders/roles.py
uvicore/auth/database/seeders/users.py
uvicore/auth/database/tables/__init__.py
uvicore/auth/database/tables/group_roles.py
uvicore/auth/database/tables/groups.py
uvicore/auth/database/tables/permissions.py
uvicore/auth/database/tables/role_permissions.py
uvicore/auth/database/tables/roles.py
uvicore/auth/database/tables/user_groups.py
uvicore/auth/database/tables/user_roles.py
uvicore/auth/database/tables/users.py
uvicore/auth/http/api/userinfo.py
uvicore/auth/http/public/assets/js/app.js
uvicore/auth/http/public/robots.txt
uvicore/auth/http/public/test.txt
uvicore/auth/http/routes/api.py
uvicore/auth/models/__init__.py
uvicore/auth/models/group.py
uvicore/auth/models/permission.py
uvicore/auth/models/role.py
uvicore/auth/models/user.py
uvicore/auth/package/provider.py
uvicore/auth/support/password.py
uvicore/auth/user_info.py
uvicore/auth/user_providers/__init__.py
uvicore/auth/user_providers/jwt.py
uvicore/auth/user_providers/orm.py
uvicore/cache/backends/array.py
uvicore/cache/backends/redis.py
uvicore/cache/manager.py
uvicore/cache/package/provider.py
uvicore/configuration/__init__.py
uvicore/configuration/commands/config.py
uvicore/configuration/configuration.py
uvicore/configuration/package/provider.py
uvicore/console/__init__.py
uvicore/console/asyncclick/LICENSE.rst
uvicore/console/asyncclick/README.md
uvicore/console/asyncclick/__init__.py
uvicore-0.3.17.dist-info/METADATA
uvicore-0.3.17.dist-info/WHEEL
uvicore-0.3.17.dist-info/licenses/LICENSE
uvicore-0.3.17.dist-info/RECORD
