Metadata-Version: 2.4
Name: uvicore
Version: 0.3.17
Summary: The Fullstack Async Web, API and CLI Python Framework
License-Expression: MIT
License-File: LICENSE
Author: Matthew Reschke
Author-email: mail@mreschke.com
Requires-Python: >=3.10
Classifier: Development Status :: 2 - Pre-Alpha
Classifier: Environment :: Web Environment
Classifier: Environment :: Console
Classifier: Framework :: AnyIO
Classifier: Framework :: FastAPI
Classifier: Framework :: Pydantic
Classifier: Intended Audience :: Developers
Classifier: Intended Audience :: Information Technology
Classifier: Intended Audience :: System Administrators
Classifier: License :: OSI Approved :: MIT License
Classifier: Operating System :: OS Independent
Classifier: Topic :: Internet
Classifier: Topic :: Internet :: WWW/HTTP
Classifier: Topic :: Internet :: WWW/HTTP :: HTTP Servers
Classifier: Topic :: Software Development
Classifier: Topic :: Software Development :: Libraries
Classifier: Topic :: Software Development :: Libraries :: Python Modules
Classifier: Topic :: Software Development :: Libraries :: Application Frameworks
Classifier: Typing :: Typed
Provides-Extra: database
Provides-Extra: redis
Provides-Extra: web
Requires-Dist: Mako (==1.3.10)
Requires-Dist: MarkupSafe (==3.0.3)
Requires-Dist: PyMySQL (==1.1.2)
Requires-Dist: Pygments (==2.19.2)
Requires-Dist: aiofiles (==24.1.0) ; extra == "web"
Requires-Dist: aiohappyeyeballs (==2.6.1)
Requires-Dist: aiohttp (==3.11.*)
Requires-Dist: aiomysql (==0.2.*) ; extra == "database"
Requires-Dist: aiosignal (==1.4.0)
Requires-Dist: aiosqlite (==0.20.*) ; extra == "database"
Requires-Dist: alembic (==1.14.*) ; extra == "database"
Requires-Dist: anyio (==4.8.*)
Requires-Dist: argon2-cffi (==23.1.*)
Requires-Dist: asyncpg (==0.30.*) ; extra == "database"
Requires-Dist: attrs (==25.3.0)
Requires-Dist: certifi (==2025.8.3)
Requires-Dist: cffi (==2.0.0)
Requires-Dist: charset-normalizer (==3.4.3)
Requires-Dist: click (==8.3.0)
Requires-Dist: colored (==2.2.*)
Requires-Dist: colorful (==0.5.7)
Requires-Dist: coverage (==7.10.7)
Requires-Dist: cryptography (==44.0.*)
Requires-Dist: environs (==14.1.*)
Requires-Dist: fastapi (==0.115.7) ; extra == "web"
Requires-Dist: frozenlist (==1.7.0)
Requires-Dist: greenlet (==3.2.4)
Requires-Dist: gunicorn (==23.0.0) ; extra == "web"
Requires-Dist: h11 (==0.16.0)
Requires-Dist: httpcore (==1.0.9)
Requires-Dist: httptools (==0.6.4) ; extra == "web"
Requires-Dist: httpx (==0.26.*)
Requires-Dist: idna (==3.10)
Requires-Dist: iniconfig (==2.1.0)
Requires-Dist: itsdangerous (==2.2.0) ; extra == "web"
Requires-Dist: jinja2 (==3.1.5)
Requires-Dist: marshmallow (==4.0.1)
Requires-Dist: merge-args (==0.1.*)
Requires-Dist: multidict (==6.6.4)
Requires-Dist: packaging (==25.0)
Requires-Dist: pluggy (==1.6.0)
Requires-Dist: prettyprinter (==0.18.*)
Requires-Dist: propcache (==0.3.2)
Requires-Dist: pycparser (==2.23)
Requires-Dist: pydantic (==1.10.*)
Requires-Dist: pyjwt (==2.10.1) ; extra == "web"
Requires-Dist: python-dotenv (==1.1.1)
Requires-Dist: python-multipart (==0.0.20) ; extra == "web"
Requires-Dist: redis[hiredis] (==5.2.*) ; extra == "redis"
Requires-Dist: requests (==2.32.3) ; extra == "web"
Requires-Dist: sniffio (==1.3.1)
Requires-Dist: sqlalchemy (==2.0.*) ; extra == "database"
Requires-Dist: starlette (==0.45.3) ; extra == "web"
Requires-Dist: typing_extensions (==4.15.0)
Requires-Dist: urllib3 (==2.5.0)
Requires-Dist: uvicorn (==0.34.0) ; extra == "web"
Requires-Dist: uvloop (==0.21.0) ; extra == "web"
Requires-Dist: yarl (==1.20.1)
Project-URL: Documentation, https://github.com/uvicore/framework
Project-URL: Homepage, https://github.com/uvicore/framework
Project-URL: Repository, https://github.com/uvicore/framework
